BookerTrans/__init__.py
BookerTrans/__main__.py
BookerTrans/config.py
BookerTrans/util.py
BookerTrans/apis/AliTransSeleniumApi.py
BookerTrans/apis/BaiTransSeleniumApi.py
BookerTrans/apis/BingTransSeleniumApi.py
BookerTrans/apis/DeeplTransSeleniumApi.py
BookerTrans/apis/GoTransSeleniumApi.py
BookerTrans/apis/QTransSeleniumApi.py
BookerTrans/apis/SeleniumApi.py
BookerTrans/apis/SoTransSeleniumApi.py
BookerTrans/apis/YoudaoTransApi.py
BookerTrans/apis/YoudaoTransSeleniumApi.py
BookerTrans/apis/__init__.py
BookerTrans/apis/stealth.min.js
BookerTrans-2023.2.21.8.dist-info/LICENSE
BookerTrans-2023.2.21.8.dist-info/METADATA
BookerTrans-2023.2.21.8.dist-info/WHEEL
BookerTrans-2023.2.21.8.dist-info/entry_points.txt
BookerTrans-2023.2.21.8.dist-info/top_level.txt
BookerTrans-2023.2.21.8.dist-info/RECORD
