Metadata-Version: 2.1
Name: BookerTrans
Version: 2023.2.21.8
Summary: HTML Translator with Google Api for iBooker/ApacheCN
Home-page: https://github.com/apachecn/BookerTrans
Author: ApacheCN
Author-email: apachecn@163.com
License: UNKNOWN
Keywords: google,html,translate,translater,谷歌,翻译
Platform: UNKNOWN
Classifier: Development Status :: 4 - Beta
Classifier: Environment :: Console
Classifier: Intended Audience :: Developers
Classifier: Intended Audience :: End Users/Desktop
Classifier: License :: Other/Proprietary License
Classifier: Natural Language :: Chinese (Simplified)
Classifier: Natural Language :: English
Classifier: Operating System :: OS Independent
Classifier: Programming Language :: Python :: 3
Classifier: Programming Language :: Python :: 3 :: Only
Classifier: Programming Language :: Python :: 3.6
Classifier: Programming Language :: Python :: 3.7
Classifier: Topic :: Internet :: WWW/HTTP
Classifier: Topic :: Text Processing :: Markup :: HTML
Classifier: Topic :: Software Development :: Documentation
Classifier: Topic :: Software Development :: Localization
Classifier: Topic :: Utilities
Requires-Python: >=3.6
Requires-Dist: requests
Requires-Dist: pyquery
Requires-Dist: selenium
Requires-Dist: PyExecJS
